ray_map.py
ray_map-0.1.1.dist-info/licenses/LICENSE
ray_map-0.1.1.dist-info/METADATA
ray_map-0.1.1.dist-info/WHEEL
ray_map-0.1.1.dist-info/top_level.txt
ray_map-0.1.1.dist-info/RECORD
