Metadata-Version: 2.4
Name: ray-map
Version: 0.1.1
Summary: Efficient Ray-powered map/imap with backpressure, checkpointing, timeouts, and async
Author-email: Your Name <your.email@example.com>
License: MIT License
Project-URL: Homepage, https://github.com/TovarnovM/ray_map
Project-URL: Source, https://github.com/TovarnovM/ray_map
Project-URL: Issues, https://github.com/TovarnovM/ray_map/issues
Keywords: ray,parallel,map,distributed-computing,async
Classifier: Programming Language :: Python :: 3
Classifier: Programming Language :: Python :: 3 :: Only
Classifier: License :: OSI Approved :: MIT License
Classifier: Operating System :: OS Independent
Classifier: Topic :: Software Development :: Libraries
Classifier: Topic :: System :: Distributed Computing
Requires-Python: >=3.9
License-File: LICENSE
Requires-Dist: ray>=2.6
Requires-Dist: cloudpickle>=2.2
Provides-Extra: dev
Requires-Dist: pytest>=7.0; extra == "dev"
Requires-Dist: pytest-timeout>=2.1; extra == "dev"
Requires-Dist: ruff>=0.5; extra == "dev"
Requires-Dist: black>=24.0; extra == "dev"
Requires-Dist: mypy>=1.8; extra == "dev"
Requires-Dist: build>=1.2; extra == "dev"
Requires-Dist: twine>=5.0; extra == "dev"
Dynamic: license-file
